CHANGELOG.txt
LICENCE.txt
MANIFEST.in
README.md
commands.txt
run.py
setup.py
dateUts/__init__.py
dateUts.egg-info/PKG-INFO
dateUts.egg-info/SOURCES.txt
dateUts.egg-info/dependency_links.txt
dateUts.egg-info/requires.txt
dateUts.egg-info/top_level.txt