Metadata-Version: 2.1
Name: dateUts
Version: 0.3.2
Summary: Date package
Home-page: 
Author: Melque Lima
Author-email: melque_ex@yahoo.com.br
License: MIT
Keywords: dateUts
Classifier: Development Status :: 5 - Production/Stable
Classifier: Intended Audience :: Education
Classifier: Operating System :: Microsoft :: Windows :: Windows 10
Classifier: License :: OSI Approved :: MIT License
Classifier: Programming Language :: Python :: 3
License-File: LICENCE.txt
Requires-Dist: python-dateutil==2.8.2
